audio_libs_tlk/__init__.py
audio_libs_tlk/convertion_functions.py
audio_libs_tlk/edit_cover_artwork.py
audio_libs_tlk/folder_lib_scan.py
audio_libs_tlk/itunes_lib_scan.py
audio_libs_tlk/lib_scan.py
audio_libs_tlk/parameters.py
audio_libs_tlk/processing_lib.py
audio_libraries_tlk-1.2.2.dist-info/LICENCE
audio_libraries_tlk-1.2.2.dist-info/METADATA
audio_libraries_tlk-1.2.2.dist-info/WHEEL
audio_libraries_tlk-1.2.2.dist-info/top_level.txt
audio_libraries_tlk-1.2.2.dist-info/RECORD
